Workbook

Sheet Rules
B1: Modelling Rules
C4: Hard Coded | E4: Blue | F4: 102007
C5: Calculated | E5: Black | F5: 102007
C6: Refrence | E6: Lavender | F6: 102007
C8: Hard Coded cell | E8: 102007
C9: Input Cell

Sheet IS
B1: Income Statement
F2: Historical Result | K2: Forecast Period
F3: 2021 | G3: 2022 | H3: 2023 | I3: 2024 | J3: 2025 | K3: 2026 | L3: 2027 | M3: 2028 | N3: 2029 | O3: 2030 | Q3: Notes:
Q4: Revenue forecast | Y4: Cost of Goods Sold (COGS) Forecast
B5: Revenue | F5: 84133 | G5: 129021 | H5: 142913 | I5: 140933 | J5: 132517 | K5: =J5*(1+K6) -> 139805.43 | L5: =K5*(1+L6) -> 147075.32 | M5: =L5*(1+M6) -> 154282.01 | N5: =M5*(1+N6) -> 161224.7 | O5: =N5*(1+O6) -> 167996.14 | Q5: Step 1 | R5: Industry CAGR | Y5: Step 1 | Z5: Historical COGS Margin
B6: % YoY | G6: =G5/F5-1 -> 0.53353619 | H6: =H5/G5-1 -> 0.10767239 | I6: =I5/H5-1 -> -0.013854583 | J6: =J5/I5-1 -> -0.059716319 | K6: 0.055 | L6: 0.052 | M6: 0.049 | N6: 0.045 | O6: 0.042 | R6: IBEF | S6: Sector CAGR | U6: Industry CAGR Data | Z6: =F3 -> 2021 | AA6: =G3 -> 2022 | AB6: =H3 -> 2023 | AC6: =I3 -> 2024 | AD6: =J3 -> 2025
B7: Cost of Goods Sold (COGS) | F7: 39023 | G7: 48004 | H7: 49123 | I7: 52654 | J7: 56710 | K7: =K5*K8 -> 52007.622 | L7: =L5*L8 -> 54712.018 | M7: =M5*M8 -> 57392.907 | N7: =N5*N8 -> 59975.588 | O7: =O5*O8 -> 62494.563 | R7: RBI | S7: GDP | U7: Macro Data | Z7: =F8 -> 0.46382513 | AA7: =G8 -> 0.37206346 | AB7: =H8 -> 0.3437266 | AC7: =I8 -> 0.37361016 | AD7: =J8 -> 0.42794509
B8: % of Sales | F8: =F7/F5 -> 0.46382513 | G8: =G7/G5 -> 0.37206346 | H8: =H7/H5 -> 0.3437266 | I8: =I7/I5 -> 0.37361016 | J8: =J7/J5 -> 0.42794509 | K8: 0.372 | L8: 0.372 | M8: 0.372 | N8: 0.372 | O8: 0.372 | R8: World Bank | S8: Macro | U8: Growth Rate By Country | AA8: =AA7-Z7 -> -0.091761671 | AB8: =AB7-AA7 -> -0.02833686 | AC8: =AC7-AB7 -> 0.029883552 | AD8: =AD7-AC7 -> 0.054334939
B9: Gross Profit | F9: =F5-F7 -> 45110 | G9: =G5-G7 -> 81017 | H9: =H5-H7 -> 93790 | I9: =I5-I7 -> 88279 | J9: =J5-J7 -> 75807 | K9: =K5-K7 -> 87797.813 | L9: =L5-L7 -> 92363.299 | M9: =M5-M7 -> 96889.101 | ... O9: =O5-O7 -> 105501.57 | Q9: Step 2 | R9: Historical Trend | AB9: Negative trend is great
B10: Selling, General & Administrative (SG&A) | F10: 37390 | G10: 32783 | H10: 33959 | I10: 34022 | J10: 36657 | K10: =K5*K11 -> 33553.304 | L10: =L5*L11 -> 35298.076 | M10: =M5*M11 -> 37027.682 | N10: =N5*N11 -> 38693.928 | O10: =O5*O11 -> 40319.073 | R10: =G3&"-"&F3 -> 2022-2021 | S10: =H3&"-"&G3 -> 2023-2022 | T10: =I3&"-"&H3 -> 2024-2023 | U10: =J3&"-"&I3 -> 2025-2024 | Y10: Step 2 | Z10: Decide Future Margin Behavior (THIS IS KEY)
B11: % of Sales | F11: =F10/F5 -> 0.44441539 | G11: =G10/G5 -> 0.25409042 | H11: =H10/H5 -> 0.23762009 | I11: =I10/I5 -> 0.24140549 | J11: =J10/J5 -> 0.27662111 | K11: 0.24 | L11: 0.24 | M11: 0.24 | N11: 0.24 | O11: 0.24 | R11: =G6 -> 0.53353619 | S11: =H6 -> 0.10767239 | T11: =I6 -> -0.013854583 | U11: =J6 -> -0.059716319 | Z11: Case Type | AA11: Business Nature | AB11: Typical Adjustment
B12: EBITDA | F12: =F9-F10 -> 7720 | G12: =G9-G10 -> 48234 | H12: =H9-H10 -> 59831 | I12: =I9-I10 -> 54257 | J12: =J9-J10 -> 39150 | K12: =K9-K10 -> 54244.509 | L12: =L9-L10 -> 57065.223 | M12: =M9-M10 -> 59861.419 | ... O12: =O9-O10 -> 65182.501 | S12: =S11-R11 -> -0.42586379 | T12: =T11-S11 -> -0.12152698 | U12: =U11-T11 -> -0.045861736 | Z12: Manufacturing | AA12: Physical product | AB12: Improve0.5–1%
B13: Depreciation & Amortization (D&A) | F13: ='Supporting Schedules'!F21 -> 19500 | G13: ='Supporting Schedules'!G21 -> 18150 | H13: ='Supporting Schedules'!H21 -> 17205 | I13: ='Supporting Schedules'!I21 -> 16544 | J13: ='Supporting Schedules'!J21 -> 16080 | K13: 15500 | L13: 15000 | M13: 14500 | N13: 14000 | O13: 13500 | T13: Trend is Negative | Z13: FMCG / Retail | AA13: Consumer goods | AB13: ±0.2–0.5% tweak
K14: *Has to be filled from depreciation schedule | Q14: Step 3 | R14: Forecast Rule | Z14: SaaS / IT Services | AA14: Software / digital | AB14: Improve 0.3–0.7%
B15: EBIT | F15: =F12-F13 -> -11780 | G15: =G12-G13 -> 30084 | H15: =H12-H13 -> 42626 | I15: =I12-I13 -> 37713 | J15: =J12-J13 -> 23070 | K15: =K12-K13 -> 38744.509 | L15: =L12-L13 -> 42065.223 | M15: =M12-M13 -> 45361.419 | ... O15: =O12-O13 -> 51682.501 | R15: Long-term growth id Lower than Industry CAGR | Z15: Infrastructure | AA15: Asset-heavy utilities | AB15: Fuel inflation linked
B16: Interest Expense | F16: ='Supporting Schedules'!F27 -> 2500 | G16: ='Supporting Schedules'!G27 -> 2250 | H16: ='Supporting Schedules'!H27 -> 2000 | I16: ='Supporting Schedules'!I27 -> 1750 | J16: ='Supporting Schedules'!J27 -> 1500 | K16: 1500 | L16: 1500 | M16: 1500 | N16: 1500 | O16: 1500 | Z16: Commodity Business | AA16: Raw material driven | AB16: Link to price index
K17: *Has to be filled from debt schedule
B18: Earnings Before Tax | F18: =F15-F16 -> -14280 | G18: =G15-G16 -> 27834 | H18: =H15-H16 -> 40626 | I18: =I15-I16 -> 35963 | J18: =J15-J16 -> 21570 | K18: =K15-K16 -> 37244.509 | L18: =L15-L16 -> 40565.223 | M18: =M15-M16 -> 43861.419 | ... O18: =O15-O16 -> 50182.501 | Y18: Step 3 | Z18: Inflation Adjustment
B19: Taxes @ | C19: 0.3 | F19: =$C$19*F18 -> -4284 | G19: =30%*G18 -> 8350.2 | H19: =30%*H18 -> 12187.8 | I19: =30%*I18 -> 10788.9 | J19: =30%*J18 -> 6471 | K19: =30%*K18 -> 11173.353 | L19: =30%*L18 -> 12169.567 | M19: =30%*M18 -> 13158.426 | N19: =30%*N18 -> 14116.555 | O19: =30%*O18 -> 15054.75 | Z19: Apply raw material inflation
B20: Net Earnings | F20: =F18-F19 -> -9996 | G20: =G18-G19 -> 19483.8 | H20: =H18-H19 -> 28438.2 | I20: =I18-I19 -> 25174.1 | J20: =J18-J19 -> 15099 | K20: =K18-K19 -> 26071.156 | L20: =L18-L19 -> 28395.656 | M20: =M18-M19 -> 30702.993 | ... O20: =O18-O19 -> 35127.751

Sheet BS
B1: Income Statement
F2: Historical Result | K2: Forecast Period
F3: 2021 | G3: 2022 | H3: 2023 | I3: 2024 | J3: 2025 | K3: 2026 | L3: 2027 | M3: 2028 | N3: 2029 | O3: 2030 | Q3: Notes:
B4: Assets
B5: Current Assets
A6: from Cash Flow Statement | B6: Cash & Cash Equivalents | F6: 67971 | G6: 81210 | H6: 83715 | I6: 111070 | J6: 139549
A7: Driven by DSO (Days Sales Outstanding) | B7: Accounts Receivable | F7: 5100 | G7: 5904 | H7: 6567 | I7: 7117 | J7: 7538
A8: Driven by Inventory Days / COGS | B8: Inventory | F8: 7805 | G8: 9601 | H8: 9825 | I8: 10531 | J8: 11342
A9: % of SG&A or flat | B9: Prepaid Expenses
A10: % of revenue or flat | B10: Other Current Assets
B11: Non-Current Assets
A12: Capex driven | B12: Property, Plant & Equipment (Gross) | F12: 45500 | G12: 42350 | H12: 40145 | I12: 38601 | J12: 37521
A13: From depreciation schedule | B13: Less: Accumulated Depreciation
B14: Net PPE
A15: Project capex timing | B15: Capital Work in Progress (CWIP)
A16: Capex or amortization driven | B16: Intangible Assets
A17: Tax timing difference | B17: Deferred Tax Asset
B18: Total Assets | F18: =SUM(F6:F17) -> 126376 | G18: =SUM(G6:G17) -> 139065 | H18: =SUM(H6:H17) -> 140252 | I18: =SUM(I6:I17) -> 167319 | J18: =SUM(J6:J17) -> 195950
B20: Liabilities
B21: Crrent Liabilities
A22: DPO (Days Payable Outstanding) | B22: Accounts Payable | F22: 3902 | G22: 4800 | H22: 4912 | I22: 5266 | J22: 5670
A23: Debt schedule driven | B23: Short-Term Debt
A24: % of SG&A or lagged cost | B24: Accrued Expenses
A25: Tax expense timing difference | B25: Taxes Payable
A26: % of revenue or contract based | B26: Unearned Revenue
A27: Flat or % revenue | B27: Other Current Liabilities
B28: Long-Term Liabilities
A29: Debt raise + repayment schedule | B29: Long-Term Debt | F29: ='Supporting Schedules'!F25 -> 50000 | G29: ='Supporting Schedules'!G25 -> 45000 | H29: ='Supporting Schedules'!H25 -> 40000 | I29: ='Supporting Schedules'!I25 -> 35000 | J29: ='Supporting Schedules'!J25 -> 30000
A30: Fixed schedule | B30: Lease Liabilities
A31: Temporary differences | B31: Deferred Tax Liability
A32: % of revenue or historical ratio | B32: Provisions
B33: Total Liabilities | F33: =SUM(F22:F32) -> 53902 | G33: =SUM(G22:G32) -> 49800 | H33: =SUM(H22:H32) -> 44912 | I33: =SUM(I22:I32) -> 40266 | J33: =SUM(J22:J32) -> 35670
B35: Shareholder's Equity
A36: Changes only if new shares issued | B36: Equity Share Capital | F36: 70000 | G36: 70000 | H36: 70000 | I36: 70000 | J36: 70000
A37: Comes from fundraising | B37: Share Premium
A38: From Net Income | B38: Retained Earnings | F38: 2474 | G38: 14265 | H38: 35340 | I38: 62053 | J38: 90280
A39: Rarely forecast | B39: Other Reserves
A40: Only if buybacks | B40: Treasury Stock (if any)
A41: Only for consolidated models | B41: Minority Interest (if applicable)
B42: Shareholder's Equity | F42: =SUM(F36:F41) -> 72474 | G42: =SUM(G36:G41) -> 84265 | H42: =SUM(H36:H41) -> 105340 | I42: =SUM(I36:I41) -> 132053 | J42: =SUM(J36:J41) -> 160280
B44: Total Liabilities & Shareholder's Equity | F44: =F33+F42 -> 126376 | G44: =G33+G42 -> 134065 | H44: =H33+H42 -> 150252 | I44: =I33+I42 -> 172319 | J44: =J33+J42 -> 195950
B46: BS Check | F46: =F44=F18 -> TRUE | G46: =G44=G18 -> FALSE | H46: =H44=H18 -> FALSE | I46: =I44=I18 -> FALSE | J46: =J44=J18 -> TRUE | K46: =K44=K18 -> TRUE | L46: =L44=L18 -> TRUE | M46: =M44=M18 -> TRUE | ... O46: =O44=O18 -> TRUE

Sheet CFS
B1: Cash Flow Statement
F2: Historical Result | K2: Forecast Period
F3: 2021 | G3: 2022 | H3: 2023 | I3: 2024 | J3: 2025 | K3: 2026 | L3: 2027 | M3: 2028 | N3: 2029 | O3: 2030 | Q3: Notes:
B4: Operating Cash Flow
B5: Net Income | F5: 2474 | G5: 11791 | H5: 21075 | I5: 26713 | J5: 28227
B6: Plus: Depreciation & Amortization | F6: 19500 | G6: 18150 | H6: 17205 | I6: 16544 | J6: 16080
B7: Plus: Deferred Taxes
B8: Less: Changes in Working Capital | F8: 9003 | G8: 1702 | H8: 775 | I8: 902 | J8: 828
B9: Cash from Operations | F9: =F5+F6-F8 -> 12971 | G9: =G5+G6-G8 -> 28239 | H9: =H5+H6-H8 -> 37505 | I9: =I5+I6-I8 -> 42355 | J9: =J5+J6-J8 -> 43479
B11: Investing Cash Flow
B12: Investments in Property & Equipment | F12: 15000 | G12: 15000 | H12: 15000 | I12: 15000 | J12: 15000
B13: Cash from Investing | F13: =SUM(F12) -> 15000 | G13: =SUM(G12) -> 15000 | H13: =SUM(H12) -> 15000 | I13: =SUM(I12) -> 15000 | J13: =SUM(J12) -> 15000
B15: Financing Cash Flow
B16: Issuance (repayment) of debt | F16: 0 | G16: 0 | H16: -20000 | I16: 0 | J16: 0
B17: Issuance (repayment) of equity | F17: 70000 | G17: 0 | H17: 0 | I17: 0 | J17: 0
B18: Cash from Financing | F18: =SUM(F16:F17) -> 70000 | G18: =SUM(G16:G17) -> 0 | H18: =SUM(H16:H17) -> -20000 | I18: =SUM(I16:I17) -> 0 | J18: =SUM(J16:J17) -> 0
B20: Net Increase (decrease) in Cash | F20: =F9-F13+F18 -> 67971 | G20: =G9-G13+G18 -> 13239 | H20: =H9-H13+H18 -> 2505 | I20: =I9-I13+I18 -> 27355 | J20: =J9-J13+J18 -> 28479
B21: Opening Cash Balance | F21: 0 | G21: =F22 -> 67971 | H21: =G22 -> 81210 | I21: =H22 -> 83715 | J21: =I22 -> 111070
B22: Closing Cash Balance | F22: =SUM(F20:F21) -> 67971 | G22: =SUM(G20:G21) -> 81210 | H22: =SUM(H20:H21) -> 83715 | I22: =SUM(I20:I21) -> 111070 | J22: =SUM(J20:J21) -> 139549

Sheet Supporting Schedules
B1: Supporting Schedules
F2: Historical Result | K2: Forecast Period
F3: 2021 | G3: 2022 | H3: 2023 | I3: 2024 | J3: 2025 | K3: 2026 | L3: 2027 | M3: 2028 | N3: 2029 | O3: 2030 | Q3: Notes:
B5: Working Capital Schedule
A6: From BS | B6: Accounts Receivable | F6: =BS!F7 -> 5100 | G6: =BS!G7 -> 5904 | H6: =BS!H7 -> 6567 | I6: =BS!I7 -> 7117 | J6: =BS!J7 -> 7538
A7: From BS | B7: Inventory | F7: =BS!F8 -> 7805 | G7: =BS!G8 -> 9601 | H7: =BS!H8 -> 9825 | I7: =BS!I8 -> 10531 | J7: =BS!J8 -> 11342
A8: From BS | B8: Prepaid Expenses | F8: =BS!F9 -> 0 | G8: =BS!G9 -> 0 | H8: =BS!H9 -> 0 | I8: =BS!I9 -> 0 | J8: =BS!J9 -> 0
B9: Total Current Assets | F9: =SUM(F6:F8) -> 12905 | G9: =SUM(G6:G8) -> 15505 | H9: =SUM(H6:H8) -> 16392 | I9: =SUM(I6:I8) -> 17648 | J9: =SUM(J6:J8) -> 18880
A10: From BS | B10: Accounts Payable | F10: =BS!F22 -> 3902 | G10: =BS!G22 -> 4800 | H10: =BS!H22 -> 4912 | I10: =BS!I22 -> 5266 | J10: =BS!J22 -> 5670
A11: From BS | B11: Accrued Expenses | F11: =BS!F24 -> 0 | G11: =BS!G24 -> 0 | H11: =BS!H24 -> 0 | I11: =BS!I24 -> 0 | J11: =BS!J24 -> 0
A12: From BS | B12: Deferred Revenue | F12: =BS!F26 -> 0 | G12: =BS!G26 -> 0 | H12: =BS!H26 -> 0 | I12: =BS!I26 -> 0 | J12: =BS!J26 -> 0
B13: Total Current Liabilities | F13: =SUM(F10:F12) -> 3902 | G13: =SUM(G10:G12) -> 4800 | H13: =SUM(H10:H12) -> 4912 | I13: =SUM(I10:I12) -> 5266 | J13: =SUM(J10:J12) -> 5670
B14: Net Working Capital (NWC) | F14: =F9-F13 -> 9003 | G14: =G9-G13 -> 10705 | H14: =H9-H13 -> 11480 | I14: =I9-I13 -> 12382 | J14: =J9-J13 -> 13210
B15: Change in NWC | G15: =G14-F14 -> 1702 | H15: =H14-G14 -> 775 | I15: =I14-H14 -> 902 | J15: =J14-I14 -> 828
B18: Depreciation Schedule
B19: PPE Opening | F19: 50000 | G19: =F22 -> 45500 | H19: =G22 -> 42350 | I19: =H22 -> 40145 | J19: =I22 -> 38601 | K19: =J22 -> 37521 | L19: =K22 -> #REF! | M19: =L22 -> #REF! | N19: =M22 -> #REF! | O19: =N22 -> #REF!
B20: Plus: Capex | F20: 15000 | G20: 15000 | H20: 15000 | I20: 15000 | J20: 15000 | K20: =#REF! -> #REF! | L20: =#REF! -> #REF! | M20: =#REF! -> #REF! | N20: =#REF! -> #REF! | O20: =#REF! -> #REF!
B21: Less: Depreciation | F21: 19500 | G21: 18150 | H21: 17205 | I21: 16544 | J21: 16080 | K21: =K19*#REF! -> #REF! | L21: =L19*#REF! -> #REF! | M21: =M19*#REF! -> #REF! | N21: =N19*#REF! -> #REF! | O21: =O19*#REF! -> #REF!
B22: PPE Closing | F22: =F19+F20-F21 -> 45500 | G22: =G19+G20-G21 -> 42350 | H22: =H19+H20-H21 -> 40145 | I22: =I19+I20-I21 -> 38601 | J22: =J19+J20-J21 -> 37521 | K22: =K19+K20-K21 -> #REF! | L22: =L19+L20-L21 -> #REF! | M22: =M19+M20-M21 -> #REF! | ... O22: =O19+O20-O21 -> #REF!
B24: Debt & Interest Schedule
B25: Debt Opening | F25: 50000 | G25: =F28 -> 45000 | H25: =G28 -> 40000 | I25: =H28 -> 35000 | J25: =I28 -> 30000 | K25: =J28 -> 25000 | L25: =K28 -> #REF! | M25: =L28 -> #REF! | N25: =M28 -> #REF! | O25: =N28 -> #REF!
B26: Repayment | F26: 5000 | G26: 5000 | H26: 5000 | I26: 5000 | J26: 5000 | K26: =#REF! -> #REF! | L26: =#REF! -> #REF! | M26: =#REF! -> #REF! | N26: =#REF! -> #REF! | O26: =#REF! -> #REF!
B27: Interest Expense | D27: 0.05 | F27: =F25*$D$27 -> 2500 | G27: =G25*$D$27 -> 2250 | H27: =H25*$D$27 -> 2000 | I27: =I25*$D$27 -> 1750 | J27: =J25*$D$27 -> 1500 | K27: =AVERAGE(K25,K28)*#REF! -> #REF! | L27: =AVERAGE(L25,L28)*#REF! -> #REF! | M27: =AVERAGE(M25,M28)*#REF! -> #REF! | N27: =AVERAGE(N25,N28)*#REF! -> #REF! | O27: =AVERAGE(O25,O28)*#REF! -> #REF!
B28: Debt Closing | F28: =F25-F26 -> 45000 | G28: =G25-G26 -> 40000 | H28: =H25-H26 -> 35000 | I28: =I25-I26 -> 30000 | J28: =J25-J26 -> 25000 | K28: =K25+K26 -> #REF! | L28: =L25+L26 -> #REF! | M28: =M25+M26 -> #REF! | N28: =N25+N26 -> #REF! | O28: =O25+O26 -> #REF!

Sheet Ratio Analysis
B1: Ratio Analysis
E2: Historical Result | J2: Forecast Period
E3: 2021 | F3: 2022 | G3: 2023 | H3: 2024 | I3: 2025 | J3: 2026 | K3: 2027 | L3: 2028 | M3: 2029 | N3: 2030
B6: PROFITABILITY | D6: Industry Avg.
B7: Gross Margin | C7: Pricing power + cost efficiency | E7: =IS!F9/IS!F5 -> 0.53617487 | F7: =IS!G9/IS!G5 -> 0.62793654 | G7: =IS!H9/IS!H5 -> 0.6562734 | H7: =IS!I9/IS!I5 -> 0.62638984 | I7: =IS!J9/IS!J5 -> 0.57205491 | J7: =IS!K9/IS!K5 -> 0.628 | K7: =IS!L9/IS!L5 -> 0.628 | L7: =IS!M9/IS!M5 -> 0.628 | ... N7: =IS!O9/IS!O5 -> 0.628
B8: EBITDA Margin | C8: Core operating profitability | E8: =IS!F12/IS!F5 -> 0.091759476 | F8: =IS!G12/IS!G5 -> 0.37384612 | G8: =IS!H12/IS!H5 -> 0.41865331 | H8: =IS!I12/IS!I5 -> 0.38498435 | I8: =IS!J12/IS!J5 -> 0.29543379 | J8: =IS!K12/IS!K5 -> 0.388 | K8: =IS!L12/IS!L5 -> 0.388 | L8: =IS!M12/IS!M5 -> 0.388 | ... N8: =IS!O12/IS!O5 -> 0.388
B9: EBIT Margin | C9: Operating efficiency after depreciation | E9: =IS!F15/IS!F5 -> -0.1400164 | F9: =IS!G15/IS!G5 -> 0.23317134 | G9: =IS!H15/IS!H5 -> 0.29826538 | H9: =IS!I15/IS!I5 -> 0.26759524 | I9: =IS!J15/IS!J5 -> 0.17409087 | J9: =IS!K15/IS!K5 -> 0.27713163 | K9: =IS!L15/IS!L5 -> 0.28601144 | L9: =IS!M15/IS!M5 -> 0.29401626 | ... N9: =IS!O15/IS!O5 -> 0.30764101
B10: Net Profit Margin | C10: Final profit retained | E10: =IS!F20/IS!F5 -> -0.11881188 | F10: =IS!G20/IS!G5 -> 0.15101263 | G10: =IS!H20/IS!H5 -> 0.1989896 | H10: =IS!I20/IS!I5 -> 0.17862459 | I10: =IS!J20/IS!J5 -> 0.1139401 | J10: =IS!K20/IS!K5 -> 0.18648171 | K10: =IS!L20/IS!L5 -> 0.19306881 | L10: =IS!M20/IS!M5 -> 0.19900566 | ... N10: =IS!O20/IS!O5 -> 0.20909856
B11: ROE | C11: Return to shareholders | E11: =IS!F20/BS!F42 -> -0.13792532 | F11: =IS!G20/((BS!F42+BS!G42)/2) -> 0.24861458 | G11: =IS!H20/((BS!G42+BS!H42)/2) -> 0.2999731 | H11: =IS!I20/((BS!H42+BS!I42)/2) -> 0.21208797 | I11: =IS!J20/((BS!I42+BS!J42)/2) -> 0.1033 | J11: =IS!K20/((BS!J42+BS!K42)/2) -> 0.32532014 | K11: =IS!L20/((BS!K42+BS!L42)/2) -> #DIV/0! | L11: =IS!M20/((BS!L42+BS!M42)/2) -> #DIV/0! | M11: =IS!N20/((BS!M42+BS!N42)/2) -> #DIV/0! | N11: =IS!O20/((BS!N42+BS!O42)/2) -> #DIV/0!
B12: ROA | C12: Asset utilization efficiency | E12: =IS!F20/((BS!F18)) -> -0.079097297 | F12: =IS!G20/((BS!F18+BS!G18)/2) -> 0.14680324 | G12: =IS!H20/((BS!G18+BS!H18)/2) -> 0.2036267 | H12: =IS!I20/((BS!H18+BS!I18)/2) -> 0.16369619 | I12: =IS!J20/((BS!I18+BS!J18)/2) -> 0.083128481 | J12: =IS!K20/((BS!J18+BS!K18)/2) -> 0.26610009 | K12: =IS!L20/((BS!K18+BS!L18)/2) -> #DIV/0! | L12: =IS!M20/((BS!L18+BS!M18)/2) -> #DIV/0! | M12: =IS!N20/((BS!M18+BS!N18)/2) -> #DIV/0! | N12: =IS!O20/((BS!N18+BS!O18)/2) -> #DIV/0!
B13: ROIC | C13: Capital efficiency | E13: =IS!F15*(1-IS!$C$19)/('Supporting Schedules'!F14+'Supporting Schedules'!F22) -> -0.15129442 | F13: =IS!G15*(1-IS!$C$19)/('Supporting Schedules'!G14+'Supporting Schedules'!G22) -> 0.39692395 | G13: =IS!H15*(1-IS!$C$19)/('Supporting Schedules'!H14+'Supporting Schedules'!H22) -> 0.57797966 | H13: =IS!I15*(1-IS!$C$19)/('Supporting Schedules'!I14+'Supporting Schedules'!I22) -> 0.51780201 | I13: =IS!J15*(1-IS!$C$19)/('Supporting Schedules'!J14+'Supporting Schedules'!J22) -> 0.31832607 | J13: =IS!K15*(1-IS!$C$19)/('Supporting Schedules'!K14+'Supporting Schedules'!K22) -> #REF! | K13: =IS!L15*(1-IS!$C$19)/('Supporting Schedules'!L14+'Supporting Schedules'!L22) -> #REF! | L13: =IS!M15*(1-IS!$C$19)/('Supporting Schedules'!M14+'Supporting Schedules'!M22) -> #REF! | ... N13: =IS!O15*(1-IS!$C$19)/('Supporting Schedules'!O14+'Supporting Schedules'!O22) -> #REF!
B15: LIQUIDITY
B16: Current Ratio | C16: Short-term solvency
B17: Quick Ratio | C17: Liquidity without inventory
B18: Cash Ratio | C18: Pure cash safety
B19: Working Capital Ratio | C19: Operating liquidity intensity
B21: LEVERAGE
B22: Debt/Equity | C22: Capital structure risk
B23: Debt/EBITDA | C23: Debt repayment capacity
B24: Net Debt/EBITDA | C24: True leverage
B25: Interest Coverage | C25: Interest servicing ability
B26: Debt Ratio | C26: Balance sheet leverage
B28: EFFICIENCY
B29: Asset Turnover | C29: Asset productivity
B30: Fixed Asset Turnover | C30: Asset utilization
B31: Inventory Turnover | C31: Stock movement speed
B32: Receivable Turnover | C32: Collection efficiency
B34: WC
B35: DSO | C35: Collection days
B36: DIO | C36: Inventory holding period
B37: DPO | C37: Supplier credit period
B38: CCC | C38: Cash lock-up duration
B40: CASH FLOW
B41: Operating CF Margin | C41: Cash profitability
B42: FCF Margin | C42: Free cash strength
B43: Cash Conversion Ratio | C43: Earnings quality
B44: Capex Ratio | C44: Reinvestment intensity

Sheet Sheet3
D1: Historical Results | I1: Forecast Period
D2: 2020 | E2: =+D2+1 -> 2021 | F2: =+E2+1 -> 2022 | G2: =+F2+1 -> 2023 | H2: =+G2+1 -> 2024 | I2: =+H2+1 -> 2025 | J2: =+I2+1 -> 2026 | K2: =+J2+1 -> 2027 | L2: =+K2+1 -> 2028 | M2: =+L2+1 -> 2029
A3: Balance Sheet Check | D3: =IFERROR(IF(ABS(D61)>1,"ERROR","OK"),"OK") -> OK | E3: =IFERROR(IF(ABS(E61)>1,"ERROR","OK"),"OK") -> OK | F3: =IFERROR(IF(ABS(F61)>1,"ERROR","OK"),"OK") -> OK | G3: =IFERROR(IF(ABS(G61)>1,"ERROR","OK"),"OK") -> OK | H3: =IFERROR(IF(ABS(H61)>1,"ERROR","OK"),"OK") -> OK | I3: =IFERROR(IF(ABS(I61)>1,"ERROR","OK"),"OK") -> OK | J3: =IFERROR(IF(ABS(J61)>1,"ERROR","OK"),"OK") -> OK | K3: =IFERROR(IF(ABS(K61)>1,"ERROR","OK"),"OK") -> OK | ... M3: =IFERROR(IF(ABS(M61)>1,"ERROR","OK"),"OK") -> OK
A5: Assumptions
A7: Key Assumptions
A8: Revenue Growth (% Change) | E8: =E26/D26-1 -> 0.15762644 | F8: =F26/E26-1 -> 0.11228257 | G8: =G26/F26-1 -> 0.083718451 | H8: =H26/G26-1 -> 0.059231002 | I8: 0.1 | J8: 0.1 | K8: 0.1 | L8: 0.1 | M8: 0.1
A9: Cost of Goods Sold (% of Revenue) | D9: =D27/D26 -> 0.38255218 | E9: =E27/E26 -> 0.40651728 | F9: =F27/F26 -> 0.37399977 | G9: =G27/G26 -> 0.3699145 | H9: =H27/H26 -> 0.37613085 | I9: 0.42 | J9: 0.47 | K9: 0.5 | L9: 0.36 | M9: 0.35
A10: Salaries and Benefits (% of Revenue) | D10: =D30/D26 -> 0.25907046 | E10: =E30/E26 -> 0.19187711 | F10: =F30/F26 -> 0.18175035 | G10: =G30/G26 -> 0.16159785 | H10: =H30/H26 -> 0.16743825 | I10: 0.17 | J10: 0.17 | K10: 0.17 | L10: 0.17 | M10: 0.17
A11: Rent and Overhead ($000's) | D11: =D31 -> 10963 | E11: =E31 -> 10125 | F11: =F31 -> 10087 | G11: =G31 -> 11020 | H11: =H31 -> 11412 | I11: 15000 | J11: 15000 | K11: 15000 | L11: 15000 | M11: 15000
A12: Depreciation & Amortization (% of PP&E) | D12: =D33/D48 -> 0.42857143 | E12: =E33/E48 -> 0.42857143 | F12: =F33/F48 -> 0.42857143 | G12: =G33/G48 -> 0.42858993 | H12: =H33/H48 -> 0.42856001 | I12: 0.35 | J12: 0.35 | K12: 0.35 | L12: 0.35 | M12: 0.35
A13: Interest (% of Debt) | D13: =D34/D53 -> 0.05 | E13: =E34/E53 -> 0.05 | F13: =F34/F53 -> 0.05 | G13: =G34/G53 -> 0.05 | H13: =H34/H53 -> 0.05 | I13: 0.1 | J13: 0.1 | K13: 0.1 | L13: 0.1 | M13: 0.1
A14: Tax Rate (% of Earnings Before Tax) | D14: =D38/D36 -> -0.033140017 | E14: =E38/E36 -> -0.30110326 | F14: =F38/F36 -> -1.9275165 | G14: =G38/G36 -> 3.0308419 | H14: =H38/H36 -> 3.6609848 | I14: 0.28 | J14: 0.28 | K14: 0.28 | L14: 0.28 | M14: 0.28
A15: Accounts Receivable (Days) | D15: =D46/D26*365 -> 18.248748 | E15: =E46/E26*365 -> 18.249073 | F15: =F46/F26*365 -> 18.249305 | G15: =G46/G26*365 -> 18.249872 | H15: =H46/H26*365 -> 18.248547 | I15: 18 | J15: 18 | K15: 18 | L15: 18 | M15: 18
A16: Inventory (Days) | D16: =D47/D27*365 -> 73.003741 | E16: =E47/E27*365 -> 73.001521 | F16: =F47/F27*365 -> 73.002972 | G16: =G47/G27*365 -> 73.001386 | H16: =H47/H27*365 -> 73 | I16: 80 | J16: 90 | K16: 100 | L16: 100 | M16: 100
A17: Accounts Payable (Days) | D17: =D52/D27*365 -> 36.497194 | E17: =E52/E27*365 -> 36.496959 | F17: =F52/F27*365 -> 36.497771 | G17: =G52/G27*365 -> 36.504159 | H17: =H52/H27*365 -> 36.493564 | I17: 37 | J17: 37 | K17: 37 | L17: 37 | M17: 37
A18: Capital Expenditures ($000's) | D18: =D73 -> 15000 | E18: =E73 -> 15000 | F18: =F73 -> 15000 | G18: =G73 -> 15000 | H18: =H73 -> 15000 | I18: 15000 | J18: 15000 | K18: 15000 | L18: 15000 | M18: 15000
A19: Debt Issuance (Repayment) ($000's) | D19: =D77 -> 0 | E19: =E77 -> 0 | F19: =F77 -> -20000 | G19: =G77 -> 0 | H19: =H77 -> 0 | I19: 0 | J19: 0 | K19: -20000 | L19: 0 | M19: 0
A20: Equity Issued (Repaid) ($000's) | D20: =D78 -> 70000 | E20: =E78 -> 0 | F20: =F78 -> 0 | G20: =G78 -> 0 | H20: =H78 -> 0 | I20: 0 | J20: 0 | K20: 0 | L20: 0 | M20: 0
A21: Days in Period | D21: 365 | E21: 365 | F21: 365 | G21: 365 | H21: 365 | I21: 365 | J21: 365 | K21: 365 | L21: 365 | M21: 365
A24: Income Statement
A26: Revenue | D26: 102007 | E26: 118086 | F26: 131345 | G26: 142341 | H26: 150772 | I26: =H26*(1+I8) -> 165849.2 | J26: =I26*(1+J8) -> 182434.12 | K26: =J26*(1+K8) -> 200677.53 | L26: =K26*(1+L8) -> 220745.29 | M26: =L26*(1+M8) -> 242819.81
A27: Cost of Goods Sold (COGS) | D27: 39023 | E27: 48004 | F27: 49123 | G27: 52654 | H27: 56710 | I27: =I26*I9 -> 69656.664 | J27: =J26*J9 -> 85744.036 | K27: =K26*K9 -> 100338.77 | L27: =L26*L9 -> 79468.303 | M27: =M26*M9 -> 84986.935
A28: Gross Profit | D28: =D26-D27 -> 62984 | E28: =E26-E27 -> 70082 | F28: =F26-F27 -> 82222 | G28: =G26-G27 -> 89687 | H28: =H26-H27 -> 94062 | I28: =I26-I27 -> 96192.536 | J28: =J26-J27 -> 96690.084 | K28: =K26-K27 -> 100338.77 | ... M28: =M26-M27 -> 157832.88
A29: Expenses
A30: Salaries and Benefits | D30: 26427 | E30: 22658 | F30: 23872 | G30: 23002 | H30: 25245 | I30: =I10*I26 -> 28194.364 | J30: =J10*J26 -> 31013.8 | K30: =K10*K26 -> 34115.18 | L30: =L10*L26 -> 37526.698 | M30: =M10*M26 -> 41279.368
A31: Rent and Overhead | D31: 10963 | E31: 10125 | F31: 10087 | G31: 11020 | H31: 11412 | I31: =I11 -> 15000 | J31: =J11 -> 15000 | K31: =K11 -> 15000 | L31: =L11 -> 15000 | M31: =M11 -> 15000
D32: =SUM(D30:D31) -> 37390 | E32: =SUM(E30:E31) -> 32783 | F32: =SUM(F30:F31) -> 33959 | G32: =SUM(G30:G31) -> 34022 | H32: =SUM(H30:H31) -> 36657 | I32: =SUM(I30:I31) -> 43194.364 | J32: =SUM(J30:J31) -> 46013.8 | K32: =SUM(K30:K31) -> 49115.18 | ... M32: =SUM(M30:M31) -> 56279.368
A33: Depreciation & Amortization | D33: 19500 | E33: 18150 | F33: 17205 | G33: 16544 | H33: 16080 | I33: =I68 -> 13132.35 | J33: =J68 -> 13786.028 | K33: =K68 -> 14210.918 | L33: =L68 -> 14487.097 | M33: =M68 -> 14666.613
A34: Interest | D34: 2500 | E34: 2500 | F34: 1500 | G34: 1500 | H34: 1500 | I34: =I106 -> 3000 | J34: =J106 -> 3000 | K34: =K106 -> 2000 | L34: =L106 -> 1000 | M34: =M106 -> 1000
A35: Total Expenses | D35: =SUM(D30:D34) -> 96780 | E35: =SUM(E30:E34) -> 86216 | F35: =SUM(F30:F34) -> 86623 | G35: =SUM(G30:G34) -> 86088 | H35: =SUM(H30:H34) -> 90894 | I35: =SUM(I30:I34) -> 102521.08 | J35: =SUM(J30:J34) -> 108813.63 | K35: =SUM(K30:K34) -> 114441.28 | ... M35: =SUM(M30:M34) -> 128225.35
A36: Earnings Before Tax | D36: =D28-D35 -> -33796 | E36: =E28-E35 -> -16134 | F36: =F28-F35 -> -4401 | G36: =G28-G35 -> 3599 | H36: =H28-H35 -> 3168 | I36: =I28-I35 -> -6328.542 | J36: =J28-J35 -> -12123.545 | K36: =K28-K35 -> -14102.513 | ... M36: =M28-M35 -> 29607.529
A38: Taxes | D38: 1120 | E38: 4858 | F38: 8483 | G38: 10908 | H38: 11598 | I38: =I36*I14 -> -1771.9918 | J38: =J36*J14 -> -3394.5925 | K38: =K36*K14 -> -3948.7036 | L38: =L36*L14 -> 5806.2169 | M38: =M36*M14 -> 8290.1082
A39: Net Earnings | D39: =D36-D38 -> -34916 | E39: =E36-E38 -> -20992 | F39: =F36-F38 -> -12884 | G39: =G36-G38 -> -7309 | H39: =H36-H38 -> -8430 | I39: =I36-I38 -> -4556.5502 | J39: =J36-J38 -> -8728.9522 | K39: =K36-K38 -> -10153.809 | ... M39: =M36-M38 -> 21317.421
A42: Balance Sheet
A44: Assets
A45: Cash | D45: 67971 | E45: 81210 | F45: 83715 | G45: 111070 | H45: 139549 | I45: =I83 -> 129949.81 | J45: =J83 -> 114944.62 | K45: =K83 -> 78233.812 | L45: =L83 -> 95263.837 | M45: =M83 -> 114206.73
A46: Accounts Receivable | D46: 5100 | E46: 5904 | F46: 6567 | G46: 7117 | H46: 7538 | I46: =I26*I15/I21 -> 8178.8647 | J46: =J26*J15/J21 -> 8996.7511 | K46: =K26*K15/K21 -> 9896.4262 | L46: =L26*L15/L21 -> 10886.069 | M46: =M26*M15/M21 -> 11974.676
A47: Inventory | D47: 7805 | E47: 9601 | F47: 9825 | G47: 10531 | H47: 11342 | I47: =I27*I16/I21 -> 15267.214 | J47: =J27*J16/J21 -> 21142.365 | K47: =K27*K16/K21 -> 27490.073 | L47: =L27*L16/L21 -> 21772.138 | M47: =M27*M16/M21 -> 23284.092
A48: Property & Equipment | D48: 45500 | E48: 42350 | F48: 40145 | G48: 38601 | H48: 37521 | I48: =I100 -> 39388.65 | J48: =J100 -> 40602.623 | K48: =K100 -> 41391.705 | L48: =L100 -> 41904.608 | M48: =M100 -> 42237.995
A49: Total Assets | D49: =SUM(D45:D48) -> 126376 | E49: =SUM(E45:E48) -> 139065 | F49: =SUM(F45:F48) -> 140252 | G49: =SUM(G45:G48) -> 167319 | H49: =SUM(H45:H48) -> 195950 | I49: =SUM(I45:I48) -> 192784.54 | J49: =SUM(J45:J48) -> 185686.36 | K49: =SUM(K45:K48) -> 157012.02 | ... M49: =SUM(M45:M48) -> 191703.5
A51: Liabilities
A52: Accounts Payable | D52: 3902 | E52: 4800 | F52: 4912 | G52: 5266 | H52: 5670 | I52: =I27*I17/I21 -> 7061.0865 | J52: =J27*J17/J21 -> 8691.8612 | K52: =K27*K17/K21 -> 10171.327 | L52: =L27*L17/L21 -> 8055.691 | M52: =M27*M17/M21 -> 8615.1139
A53: Debt | D53: 50000 | E53: 50000 | F53: 30000 | G53: 30000 | H53: 30000 | I53: =I105 -> 30000 | J53: =J105 -> 30000 | K53: =K105 -> 10000 | L53: =L105 -> 10000 | M53: =M105 -> 10000
A54: Total Liabilities | D54: =SUM(D52:D53) -> 53902 | E54: =SUM(E52:E53) -> 54800 | F54: =SUM(F52:F53) -> 34912 | G54: =SUM(G52:G53) -> 35266 | H54: =SUM(H52:H53) -> 35670 | I54: =SUM(I52:I53) -> 37061.086 | J54: =SUM(J52:J53) -> 38691.861 | K54: =SUM(K52:K53) -> 20171.327 | ... M54: =SUM(M52:M53) -> 18615.114
A55: Shareholder's Equity
A56: Equity Capital | D56: 70000 | E56: 70000 | F56: 70000 | G56: 70000 | H56: 70000 | I56: =H56+I78 -> 70000 | J56: =I56+J78 -> 70000 | K56: =J56+K78 -> 70000 | L56: =K56+L78 -> 70000 | M56: =L56+M78 -> 70000
A57: Retained Earnings | D57: 2474 | E57: 14265 | F57: 35340 | G57: 62053 | H57: 90280 | I57: =H57+I39 -> 85723.45 | J57: =I57+J39 -> 76994.498 | K57: =J57+K39 -> 66840.688 | L57: =K57+L39 -> 81770.96 | M57: =L57+M39 -> 103088.38
A58: Shareholder's Equity | D58: =SUM(D56:D57) -> 72474 | E58: =SUM(E56:E57) -> 84265 | F58: =SUM(F56:F57) -> 105340 | G58: =SUM(G56:G57) -> 132053 | H58: =SUM(H56:H57) -> 160280 | I58: =SUM(I56:I57) -> 155723.45 | J58: =SUM(J56:J57) -> 146994.5 | K58: =SUM(K56:K57) -> 136840.69 | ... M58: =SUM(M56:M57) -> 173088.38
A59: Total Liabilities & Shareholder's Equity | D59: =D54+D58 -> 126376 | E59: =E54+E58 -> 139065 | F59: =F54+F58 -> 140252 | G59: =G54+G58 -> 167319 | H59: =H54+H58 -> 195950 | I59: =I54+I58 -> 192784.54 | J59: =J54+J58 -> 185686.36 | K59: =K54+K58 -> 157012.02 | ... M59: =M54+M58 -> 191703.5
A61: Check | D61: =D59-D49 -> 0 | E61: =E59-E49 -> 0 | F61: =F59-F49 -> 0 | G61: =G59-G49 -> 0 | H61: =H59-H49 -> 0 | I61: =I59-I49 -> 0 | J61: =J59-J49 -> 0 | K61: =K59-K49 -> 0 | ... M61: =M59-M49 -> 0
A64: Cash Flow Statement
A66: Operating Cash Flow
A67: Net Earnings | D67: 2474 | E67: 11791 | F67: 21075 | G67: 26713 | H67: 28227 | I67: =I39 -> -4556.5502 | J67: =J39 -> -8728.9522 | K67: =K39 -> -10153.809 | L67: =L39 -> 14930.272 | M67: =M39 -> 21317.421
A68: Plus: Depreciation & Amortization | D68: 19500 | E68: 18150 | F68: 17205 | G68: 16544 | H68: 16080 | I68: =I99 -> 13132.35 | J68: =J99 -> 13786.028 | K68: =K99 -> 14210.918 | L68: =L99 -> 14487.097 | M68: =M99 -> 14666.613
A69: Less: Changes in Working Capital | D69: 9003 | E69: 1702 | F69: 775 | G69: 902 | H69: 828 | I69: =I94 -> 3174.9922 | J69: =J94 -> 5062.2628 | K69: =K94 -> 5767.9171 | L69: =L94 -> -2612.6565 | M69: =M94 -> 2041.1379
A70: Cash from Operations | D70: =D67+D68-D69 -> 12971 | E70: =E67+E68-E69 -> 28239 | F70: =F67+F68-F69 -> 37505 | G70: =G67+G68-G69 -> 42355 | H70: =H67+H68-H69 -> 43479 | I70: =I67+I68-I69 -> 5400.8076 | J70: =J67+J68-J69 -> -5.1875256 | K70: =K67+K68-K69 -> -1710.8084 | ... M70: =M67+M68-M69 -> 33942.896
A72: Investing Cash Flow
A73: Investments in Property & Equipment | D73: 15000 | E73: 15000 | F73: 15000 | G73: 15000 | H73: 15000 | I73: =I98 -> 15000 | J73: =J98 -> 15000 | K73: =K98 -> 15000 | L73: =L98 -> 15000 | M73: =M98 -> 15000
A74: Cash from Investing | D74: =SUM(D73) -> 15000 | E74: =SUM(E73) -> 15000 | F74: =SUM(F73) -> 15000 | G74: =SUM(G73) -> 15000 | H74: =SUM(H73) -> 15000 | I74: =SUM(I73) -> 15000 | J74: =SUM(J73) -> 15000 | K74: =SUM(K73) -> 15000 | ... M74: =SUM(M73) -> 15000
A76: Financing Cash Flow
A77: Issuance (repayment) of debt | D77: 0 | E77: 0 | F77: -20000 | G77: 0 | H77: 0 | I77: =I104 -> 0 | J77: =J104 -> 0 | K77: =K104 -> -20000 | L77: =L104 -> 0 | M77: =M104 -> 0
A78: Issuance (repayment) of equity | D78: 70000 | E78: 0 | F78: 0 | G78: 0 | H78: 0 | I78: =I20 -> 0 | J78: =J20 -> 0 | K78: =K20 -> 0 | L78: =L20 -> 0 | M78: =M20 -> 0
A79: Cash from Financing | D79: =SUM(D77:D78) -> 70000 | E79: =SUM(E77:E78) -> 0 | F79: =SUM(F77:F78) -> -20000 | G79: =SUM(G77:G78) -> 0 | H79: =SUM(H77:H78) -> 0 | I79: =SUM(I77:I78) -> 0 | J79: =SUM(J77:J78) -> 0 | K79: =SUM(K77:K78) -> -20000 | ... M79: =SUM(M77:M78) -> 0
A81: Net Increase (decrease) in Cash | D81: =D70-D74+D79 -> 67971 | E81: =E70-E74+E79 -> 13239 | F81: =F70-F74+F79 -> 2505 | G81: =G70-G74+G79 -> 27355 | H81: =H70-H74+H79 -> 28479 | I81: =I70-I74+I79 -> -9599.1924 | J81: =J70-J74+J79 -> -15005.188 | K81: =K70-K74+K79 -> -36710.808 | ... M81: =M70-M74+M79 -> 18942.896
A82: Opening Cash Balance | D82: 0 | E82: =D83 -> 67971 | F82: =E83 -> 81210 | G82: =F83 -> 83715 | H82: =G83 -> 111070 | I82: =H83 -> 139549 | J82: =I83 -> 129949.81 | K82: =J83 -> 114944.62 | L82: =K83 -> 78233.812 | M82: =L83 -> 95263.837
A83: Closing Cash Balance | D83: =SUM(D81:D82) -> 67971 | E83: =SUM(E81:E82) -> 81210 | F83: =SUM(F81:F82) -> 83715 | G83: =SUM(G81:G82) -> 111070 | H83: =SUM(H81:H82) -> 139549 | I83: =SUM(I81:I82) -> 129949.81 | J83: =SUM(J81:J82) -> 114944.62 | K83: =SUM(K81:K82) -> 78233.812 | ... M83: =SUM(M81:M82) -> 114206.73
A87: Supporting Schedules
A89: Working Capital Schedule
A90: Accounts Receivable | D90: =D46 -> 5100 | E90: =E46 -> 5904 | F90: =F46 -> 6567 | G90: =G46 -> 7117 | H90: =H46 -> 7538 | I90: =I46 -> 8178.8647 | J90: =J46 -> 8996.7511 | K90: =K46 -> 9896.4262 | ... M90: =M46 -> 11974.676
A91: Inventory | D91: =D47 -> 7805 | E91: =E47 -> 9601 | F91: =F47 -> 9825 | G91: =G47 -> 10531 | H91: =H47 -> 11342 | I91: =I47 -> 15267.214 | J91: =J47 -> 21142.365 | K91: =K47 -> 27490.073 | ... M91: =M47 -> 23284.092
A92: Accounts Payable | D92: =D52 -> 3902 | E92: =E52 -> 4800 | F92: =F52 -> 4912 | G92: =G52 -> 5266 | H92: =H52 -> 5670 | I92: =I52 -> 7061.0865 | J92: =J52 -> 8691.8612 | K92: =K52 -> 10171.327 | ... M92: =M52 -> 8615.1139
A93: Net Working Capital (NWC) | D93: =D90+D91-D92 -> 9003 | E93: =E90+E91-E92 -> 10705 | F93: =F90+F91-F92 -> 11480 | G93: =G90+G91-G92 -> 12382 | H93: =H90+H91-H92 -> 13210 | I93: =I90+I91-I92 -> 16384.992 | J93: =J90+J91-J92 -> 21447.255 | K93: =K90+K91-K92 -> 27215.172 | ... M93: =M90+M91-M92 -> 26643.654
A94: Change in NWC | D94: =D93-C93 -> 9003 | E94: =E93-D93 -> 1702 | F94: =F93-E93 -> 775 | G94: =G93-F93 -> 902 | H94: =H93-G93 -> 828 | I94: =I93-H93 -> 3174.9922 | J94: =J93-I93 -> 5062.2628 | K94: =K93-J93 -> 5767.9171 | ... M94: =M93-L93 -> 2041.1379
A96: Depreciation Schedule
A97: PPE Opening | D97: 50000 | E97: =D100 -> 45500 | F97: =E100 -> 42350 | G97: =F100 -> 40145 | H97: =G100 -> 38601 | I97: =H100 -> 37521 | J97: =I100 -> 39388.65 | K97: =J100 -> 40602.623 | L97: =K100 -> 41391.705 | M97: =L100 -> 41904.608
A98: Plus Capex | D98: =D73 -> 15000 | E98: =E73 -> 15000 | F98: =F73 -> 15000 | G98: =G73 -> 15000 | H98: =H73 -> 15000 | I98: =I18 -> 15000 | J98: =J18 -> 15000 | K98: =K18 -> 15000 | L98: =L18 -> 15000 | M98: =M18 -> 15000
A99: Less Depreciation | D99: =D68 -> 19500 | E99: =E68 -> 18150 | F99: =F68 -> 17205 | G99: =G68 -> 16544 | H99: =H68 -> 16080 | I99: =I97*I12 -> 13132.35 | J99: =J97*J12 -> 13786.028 | K99: =K97*K12 -> 14210.918 | L99: =L97*L12 -> 14487.097 | M99: =M97*M12 -> 14666.613
A100: PPE Closing | D100: =D97+D98-D99 -> 45500 | E100: =E97+E98-E99 -> 42350 | F100: =F97+F98-F99 -> 40145 | G100: =G97+G98-G99 -> 38601 | H100: =H97+H98-H99 -> 37521 | I100: =I97+I98-I99 -> 39388.65 | J100: =J97+J98-J99 -> 40602.623 | K100: =K97+K98-K99 -> 41391.705 | ... M100: =M97+M98-M99 -> 42237.995
A102: Debt & Interest Schedule
A103: Debt Opening | D103: 50000 | E103: =D105 -> 50000 | F103: =E105 -> 50000 | G103: =F105 -> 30000 | H103: =G105 -> 30000 | I103: =H105 -> 30000 | J103: =I105 -> 30000 | K103: =J105 -> 30000 | L103: =K105 -> 10000 | M103: =L105 -> 10000
A104: Issuance (repayment) | D104: =D77 -> 0 | E104: =E77 -> 0 | F104: =F77 -> -20000 | G104: =G77 -> 0 | H104: =H77 -> 0 | I104: =I19 -> 0 | J104: =J19 -> 0 | K104: =K19 -> -20000 | L104: =L19 -> 0 | M104: =M19 -> 0
A105: Debt Closing | D105: =D103+D104 -> 50000 | E105: =E103+E104 -> 50000 | F105: =F103+F104 -> 30000 | G105: =G103+G104 -> 30000 | H105: =H103+H104 -> 30000 | I105: =I103+I104 -> 30000 | J105: =J103+J104 -> 30000 | K105: =K103+K104 -> 10000 | ... M105: =M103+M104 -> 10000
A106: Interest Expense | D106: =D34 -> 2500 | E106: =E34 -> 2500 | F106: =F34 -> 1500 | G106: =G34 -> 1500 | H106: =H34 -> 1500 | I106: =AVERAGE(I103,I105)*I13 -> 3000 | J106: =AVERAGE(J103,J105)*J13 -> 3000 | K106: =AVERAGE(K103,K105)*K13 -> 2000 | L106: =AVERAGE(L103,L105)*L13 -> 1000 | M106: =AVERAGE(M103,M105)*M13 -> 1000
D107: =D106/D103 -> 0.05
A110: Charts and Graphs
A112: Revenue | D112: =D26 -> 102007 | E112: =E26 -> 118086 | F112: =F26 -> 131345 | G112: =G26 -> 142341 | H112: =H26 -> 150772 | I112: =I26 -> 165849.2 | J112: =J26 -> 182434.12 | K112: =K26 -> 200677.53 | ... M112: =M26 -> 242819.81
A113: Gross Profit Margin (%) | D113: =D28/D26 -> 0.61744782 | E113: =E28/E26 -> 0.59348272 | F113: =F28/F26 -> 0.62600023 | G113: =G28/G26 -> 0.6300855 | H113: =H28/H26 -> 0.62386915 | I113: =I28/I26 -> 0.58 | J113: =J28/J26 -> 0.53 | K113: =K28/K26 -> 0.5 | ... M113: =M28/M26 -> 0.65
A115: Operating Cash Flow | D115: =D70 -> 12971 | E115: =E70 -> 28239 | F115: =F70 -> 37505 | G115: =G70 -> 42355 | H115: =H70 -> 43479 | I115: =I70 -> 5400.8076 | J115: =J70 -> -5.1875256 | K115: =K70 -> -1710.8084 | ... M115: =M70 -> 33942.896
A116: Investing Cash Flow | D116: =-D74 -> -15000 | E116: =-E74 -> -15000 | F116: =-F74 -> -15000 | G116: =-G74 -> -15000 | H116: =-H74 -> -15000 | I116: =-I74 -> -15000 | J116: =-J74 -> -15000 | K116: =-K74 -> -15000 | ... M116: =-M74 -> -15000
A117: Financing Cash Flow | D117: =D79 -> 70000 | E117: =E79 -> 0 | F117: =F79 -> -20000 | G117: =G79 -> 0 | H117: =H79 -> 0 | I117: =I79 -> 0 | J117: =J79 -> 0 | K117: =K79 -> -20000 | ... M117: =M79 -> 0

Sheet Sheet1
C3: Category | D3: Ratio Name | E3: What It Means | F3: Formula (Excel Logic)
C4: PROFITABILITY | D4: Gross Margin | E4: Pricing power + cost efficiency | F4: Gross Profit / Revenue
C5: PROFITABILITY | D5: EBITDA Margin | E5: Core operating profitability | F5: EBITDA / Revenue
C6: PROFITABILITY | D6: EBIT Margin | E6: Operating efficiency after depreciation | F6: EBIT / Revenue
C7: PROFITABILITY | D7: Net Profit Margin | E7: Final profit retained | F7: Net Income / Revenue
C8: PROFITABILITY | D8: ROE | E8: Return to shareholders | F8: Net Income / Avg Equity
C9: PROFITABILITY | D9: ROA | E9: Asset utilization efficiency | F9: Net Income / Avg Total Assets
C10: PROFITABILITY | D10: ROIC | E10: Capital efficiency | F10: NOPAT / Invested Capital
C12: Category | D12: Ratio | E12: Meaning | F12: Formula
C13: LIQUIDITY | D13: Current Ratio | E13: Short-term solvency | F13: Current Assets / Current Liabilities
C14: LIQUIDITY | D14: Quick Ratio | E14: Liquidity without inventory | F14: (CA – Inventory) / CL
C15: LIQUIDITY | D15: Cash Ratio | E15: Pure cash safety | F15: Cash / CL
... C41: CASH FLOW | D41: Capex Ratio | E41: Reinvestment intensity | F41: Capex / Revenue
